{
	"String": [
		{
			"id": 9825001,
			"string": "神殿入口的門已開啟"
		},
		{
			"id": 9825002,
			"string": "泥人怪修理裝置已啟動"
		},
		{
			"id": 9825003,
			"string": "泥人怪整修裝置已啟動"
		},
		{
			"id": 9825004,
			"string": "泥人怪生產裝置已啟動"
		},
		{
			"id": 9825005,
			"string": "稍後將會供電給左側池塘"
		},
		{
			"id": 9825006,
			"string": "左側池塘已斷電"
		},
		{
			"id": 9825007,
			"string": "稍後將會供電給右側池塘"
		},
		{
			"id": 9825008,
			"string": "右側池塘已斷電"
		},
		{
			"id": 9825027,
			"string": "一波怪物出現，需啟動左右把手，並把怪物引誘到水中。"
		},
		{
			"id": 9825009,
			"string": "開始"
		},
		{
			"id": 9825010,
			"string": "準備第二局"
		},
		{
			"id": 9825011,
			"string": "準備第三局"
		},
		{
			"id": 9825012,
			"string": "清除"
		},
		{
			"id": 9825013,
			"string": "破壞4號罈 "
		},
		{
			"id": 9825014,
			"string": "破壞5號罈 "
		},
		{
			"id": 9825015,
			"string": "神殿的守護者們蜂擁而至"
		},
		{
			"id": 9825016,
			"string": "更多守護者們蜂擁而至"
		},
		{
			"id": 9825017,
			"string": "更多守護者們蜂擁而至"
		},
		{
			"id": 9825018,
			"string": "在鏡子上反射光芒"
		},
		{
			"id": 9825019,
			"string": "光芒從空間內消失了"
		},
		{
			"id": 9825020,
			"string": "已啟動陷阱"
		},
		{
			"id": 9825021,
			"string": "失敗了。請重新再試一次"
		},
		{
			"id": 9825022,
			"string": "遺物守護者已將光芒全部吸收"
		},
		{
			"id": 9825023,
			"string": "門即將開啟"
		},
		{
			"id": 9825024,
			"string": "已召喚強力武器"
		},
		{
			"id": 9825025,
			"string": "從身體裡感受到泥人怪的力量"
		},
		{
			"id": 9825026,
			"string": "已召喚次元之鏡"
		},
		{
			"id": 9825101,
			"string": "1"
		},
		{
			"id": 9825102,
			"string": "2"
		},
		{
			"id": 9825103,
			"string": "3"
		},
		{
			"id": 9825104,
			"string": "4"
		},
		{
			"id": 9825105,
			"string": "5"
		},
		{
			"id": 9825106,
			"string": "6"
		},
		{
			"id": 9825107,
			"string": "7"
		},
		{
			"id": 9825108,
			"string": "8"
		},
		{
			"id": 9825109,
			"string": "9"
		},
		{
			"id": 9825110,
			"string": "10"
		}
	]
}