{
	"String": [
		{
			"id": 9981001,
			"string": "對50的執著"
		},
		{
			"id": 9981002,
			"string": "達魯坎的憤怒"
		},
		{
			"id": 9981003,
			"string": "蠶食靈魂"
		},
		{
			"id": 9981005,
			"string": "我!!",
			"styleId": 66
		},
		{
			"id": 9981006,
			"string": "要把你們這些傢伙!!",
			"styleId": 66
		},
		{
			"id": 9981007,
			"string": "弄死!!!",
			"styleId": 66
		},
		{
			"id": 9981008,
			"string": "呃啊啊啊!!! 不能再輸了!!!!!!",
			"styleId": 66
		},
		{
			"id": 9981009,
			"string": "已更換魔石。比起現有的魔石擁有更高的體力!",
			"styleId": 67
		},
		{
			"id": 9981010,
			"string": "進來時雖然可以隨心所欲，但離開時不行吧?",
			"styleId": 66
		},
		{
			"id": 9981011,
			"string": "受到魔石攻擊時，將會在原地召喚手下!",
			"styleId": 67
		},
		{
			"id": 9981021,
			"string": "弄死!!!",
			"styleId": 66
		},
		{
			"id": 9981022,
			"string": "用黑魔法坑板消滅吧!",
			"styleId": 66
		},
		{
			"id": 9981023,
			"string": "去吧! 黑魔法暴走!!",
			"styleId": 66
		},
		{
			"id": 9981024,
			"string": "爆炸吧!!!!!",
			"styleId": 66
		},
		{
			"id": 9981030,
			"string": "平衡"
		},
		{
			"id": 9981031,
			"string": "阻止也毫無用處",
			"styleId": 66
		},
		{
			"id": 9981032,
			"string": "貝里克的力量弱化了!",
			"styleId": 67
		},
		{
			"id": 9981033,
			"string": "拉坎的魔氣正在侵入宮殿!",
			"styleId": 67
		},
		{
			"id": 9981034,
			"string": "貝里克女神昏厥了",
			"styleId": 67
		},
		{
			"id": 9981035,
			"string": "拉坎的魔氣完全侵入宮殿了!",
			"styleId": 67
		},
		{
			"id": 9981036,
			"string": "葬身於祝福之中吧",
			"styleId": 66
		},
		{
			"id": 9981037,
			"string": "1分鐘後拉坎的詛咒將被啟動! 以傷害代替恢復!",
			"styleId": 67
		},
		{
			"id": 9981038,
			"string": "滾開",
			"styleId": 66
		},
		{
			"id": 9981039,
			"string": "感受神之詛咒吧",
			"styleId": 66
		},
		{
			"id": 9981040,
			"string": "沒用的傢伙們..最終還是照了我的計畫!!!",
			"styleId": 66
		},
		{
			"id": 9981041,
			"string": "長期處於拉坎的靈魂之中而被那股力量給蠶食了。",
			"styleId": 67
		},
		{
			"id": 9981042,
			"string": "任務失敗。",
			"styleId": 67
		},
		{
			"id": 9981043,
			"string": "拉坎開始對你們感興趣。",
			"styleId": 67
		},
		{
			"id": 9981044,
			"string": "拉坎希望你們彼此疏遠。",
			"styleId": 67
		},
		{
			"id": 9981045,
			"string": "拉坎希望你們聚在一起以便一次殺死。",
			"styleId": 67
		},
		{
			"id": 9981046,
			"string": "<font size='50'>受到...太多關注.....就會死....</font>",
			"styleId": 42
		},
		{
			"id": 9981047,
			"string": "<font size='50'>為了...疏遠.....赤紅閃電.......</font>",
			"styleId": 42
		},
		{
			"id": 9981048,
			"string": "<font size='50'>詛咒.....是對同伴的.....信賴..........</font>",
			"styleId": 42
		},
		{
			"id": 9981099,
			"string": "戰鬥空間即將關閉。",
			"styleId": 67
		},
		{
			"id": 9981500,
			"string": "雖然他已死，但仍然能感受到他的力量。在這裡待太久好像會有危險。"
		},
		{
			"id": 9981501,
			"string": "啊啊...貝里克大人!"
		},
		{
			"id": 9981502,
			"string": "我去將太古神石板安全還回伊露卡。到司令部再見吧。。"
		}
	]
}